[{"代號":"ASBP","名稱":"Aspire Biopharma Holdings, Inc.  - Common Stock","現價":6.68,"10D動能(%)":3096.17,"MA5乖離(%)":16.66,"妖股分數":4702.57},{"代號":"AIIO","名稱":"Robo.ai Inc. - Class B Ordinary Shares","現價":5.6,"10D動能(%)":800.32,"MA5乖離(%)":46.21,"妖股分數":1362.23},{"代號":"AEHL","名稱":"Antelope Enterprise Holdings Limited - Class A Ordinary Shares","現價":3.84,"10D動能(%)":652.94,"MA5乖離(%)":8.41,"妖股分數":1008.86},{"代號":"AGL","名稱":"agilon health, inc. Common Stock","現價":86.8,"10D動能(%)":222.2,"MA5乖離(%)":11.69,"妖股分數":374.22},{"代號":"VRAX","名稱":"Virax Biolabs Group Limited - Ordinary Shares","現價":0.23,"10D動能(%)":79.39,"MA5乖離(%)":44.35,"妖股分數":274.31},{"代號":"GCTS","名稱":"GCT Semiconductor Holding, Inc. Common Stock","現價":2.58,"10D動能(%)":73.15,"MA5乖離(%)":44.46,"妖股分數":265.33},{"代號":"AUUD","名稱":"Auddia Inc. - Common Stock","現價":2.37,"10D動能(%)":28.11,"MA5乖離(%)":44.51,"妖股分數":197.95},{"代號":"AMPG","名稱":"Amplitech Group, Inc. - Common Stock","現價":3.7,"10D動能(%)":68.18,"MA5乖離(%)":25.94,"妖股分數":193.05},{"代號":"CREG","名稱":"Smart Powerr Corp. - Common Stock","現價":0.62,"10D動能(%)":40.91,"MA5乖離(%)":37.17,"妖股分數":191.45},{"代號":"AIB","名稱":"BlockchAIn Digital Infrastructure, Inc Common Shares","現價":1.79,"10D動能(%)":46.72,"MA5乖離(%)":34.18,"妖股分數":189.72},{"代號":"ZONE","名稱":"CleanCore Solutions Inc. Class B Common Stock","現價":0.62,"10D動能(%)":100.0,"MA5乖離(%)":9.12,"妖股分數":181.91},{"代號":"FIGG","名稱":"Leverage Shares 2x Long FIG Daily ETF","現價":28.41,"10D動能(%)":43.34,"MA5乖離(%)":29.41,"妖股分數":167.96},{"代號":"GGRP","名稱":"The Glimpse Group, Inc. - Common Stock","現價":0.79,"10D動能(%)":44.95,"MA5乖離(%)":26.89,"妖股分數":161.54},{"代號":"AIFU","名稱":"AIFU Inc. - Class A Ordinary Share","現價":2.28,"10D動能(%)":66.42,"MA5乖離(%)":17.65,"妖股分數":161.4},{"代號":"SNAL","名稱":"Snail, Inc. - Class A Common Stock","現價":0.96,"10D動能(%)":62.71,"MA5乖離(%)":14.15,"妖股分數":143.59},{"代號":"IINNW","名稱":"Inspira Technologies Oxy B.H.N. Ltd. - Warrant","現價":0.08,"10D動能(%)":22.06,"MA5乖離(%)":30.09,"妖股分數":138.42},{"代號":"VIVO","名稱":"VivoPower PLC - Ordinary Shares","現價":4.82,"10D動能(%)":65.64,"MA5乖離(%)":11.32,"妖股分數":138.06},{"代號":"ASTX","名稱":"Tradr 2X Long ASTS Daily ETF","現價":34.01,"10D動能(%)":48.45,"MA5乖離(%)":16.23,"妖股分數":129.47},{"代號":"AMBQ","名稱":"Ambiq Micro, Inc. Common Stock","現價":71.34,"10D動能(%)":81.25,"MA5乖離(%)":1.09,"妖股分數":125.67},{"代號":"ALP","名稱":"Alpha Compute Corp  - Common Stock","現價":0.36,"10D動能(%)":41.8,"MA5乖離(%)":15.9,"妖股分數":118.35}]