[{"代號":"SPKLW","名稱":"Spark I Acquisition Corp. - Warrant","現價":0.93,"10D動能(%)":323.25,"MA5乖離(%)":157.06,"妖股分數":1034.59},{"代號":"ATIIW","名稱":"Archimedes Tech SPAC Partners II Co. - Warrant","現價":2.31,"10D動能(%)":285.0,"MA5乖離(%)":145.22,"妖股分數":935.78},{"代號":"RVMDW","名稱":"Revolution Medicines, Inc. - Warrant","現價":5.4,"10D動能(%)":187.23,"MA5乖離(%)":108.98,"妖股分數":662.28},{"代號":"DRTSW","名稱":"Alpha Tau Medical Ltd. - Warrant","現價":2.69,"10D動能(%)":163.73,"MA5乖離(%)":98.67,"妖股分數":590.94},{"代號":"BCARW","名稱":"D. Boral ARC Acquisition I Corp. - Warrant","現價":1.6,"10D動能(%)":128.57,"MA5乖離(%)":81.82,"妖股分數":479.22},{"代號":"CNEY","名稱":"CN Energy Group Inc. - Class A Ordinary Shares","現價":1.61,"10D動能(%)":121.46,"MA5乖離(%)":73.72,"妖股分數":440.19},{"代號":"FBYDW","名稱":"Falcon's Beyond Global, Inc. - Warrants","現價":1.97,"10D動能(%)":107.37,"MA5乖離(%)":70.71,"妖股分數":408.54},{"代號":"IINNW","名稱":"Inspira Technologies Oxy B.H.N. Ltd. - Warrant","現價":0.14,"10D動能(%)":77.13,"MA5乖離(%)":80.88,"妖股分數":398.76},{"代號":"BZFDW","名稱":"BuzzFeed, Inc. - Warrant","現價":0.03,"10D動能(%)":100.0,"MA5乖離(%)":66.67,"妖股分數":383.33},{"代號":"AIIOW","名稱":"Robo.ai Inc. - Warrant","現價":0.06,"10D動能(%)":99.34,"MA5乖離(%)":66.3,"妖股分數":381.04},{"代號":"AGL","名稱":"agilon health, inc. Common Stock","現價":88.2,"10D動能(%)":229.84,"MA5乖離(%)":8.29,"妖股分數":373.79},{"代號":"AUROW","名稱":"Aurora Innovation, Inc.  - Warrant","現價":0.49,"10D動能(%)":96.39,"MA5乖離(%)":64.65,"妖股分數":370.87},{"代號":"AMST","名稱":"Amesite Inc. - Common Stock","現價":1.73,"10D動能(%)":76.89,"MA5乖離(%)":72.93,"妖股分數":370.6},{"代號":"FACTW","名稱":"FACT II Acquisition Corp. - Warrant","現價":0.8,"10D動能(%)":95.12,"MA5乖離(%)":63.93,"妖股分數":366.45},{"代號":"GENVR","名稱":"Gen Digital Inc. - Contingent Value Rights","現價":1.01,"10D動能(%)":146.34,"MA5乖離(%)":29.45,"妖股分數":322.6},{"代號":"CORZW","名稱":"Core Scientific, Inc. - Tranche 1 Warrants","現價":16.17,"10D動能(%)":76.72,"MA5乖離(%)":53.21,"妖股分數":301.32},{"代號":"GCTS","名稱":"GCT Semiconductor Holding, Inc. Common Stock","現價":2.8,"10D動能(%)":84.21,"MA5乖離(%)":38.61,"妖股分數":261.46},{"代號":"GIPR","名稱":"Generation Income Properties Inc. - Common stock","現價":0.43,"10D動能(%)":61.28,"MA5乖離(%)":47.42,"妖股分數":257.9},{"代號":"CGCTW","名稱":"Cartesian Growth Corporation III - Warrant","現價":1.13,"10D動能(%)":61.68,"MA5乖離(%)":43.93,"妖股分數":246.27},{"代號":"NNAVW","名稱":"NextNav Inc. - Warrant","現價":11.3,"10D動能(%)":61.66,"MA5乖離(%)":43.91,"妖股分數":246.18}]